discogs.py
setup.py
discogs.egg-info/PKG-INFO
discogs.egg-info/SOURCES.txt
discogs.egg-info/dependency_links.txt
discogs.egg-info/entry_points.txt
discogs.egg-info/top_level.txt