Metadata-Version: 1.0
Name: discogs
Version: 0.2
Summary: Python interface to the Discogs music information database.
Home-page: UNKNOWN
Author: Jeremy Cantrell
Author-email: jmcantrell@gmail.com
License: UNKNOWN
Platform: UNKNOWN
Classifier: Development Status :: 4 - Beta
Classifier: Environment :: Console
Classifier: Intended Audience :: System Administrators
Classifier: License :: OSI Approved :: BSD License
Classifier: Natural Language :: English
Classifier: Operating System :: OS Independent
Classifier: Programming Language :: Python
Classifier: Topic :: Communications :: Email :: Email Clients (MUA)
Classifier: Topic :: System :: Systems Administration
Classifier: Topic :: Utilities
